Afvalwijzer/Afvalwijzer.py
Afvalwijzer/__init__.py
afvalwijzer-0.2.7.dist-info/DESCRIPTION.rst
afvalwijzer-0.2.7.dist-info/METADATA
afvalwijzer-0.2.7.dist-info/RECORD
afvalwijzer-0.2.7.dist-info/WHEEL
afvalwijzer-0.2.7.dist-info/metadata.json
afvalwijzer-0.2.7.dist-info/top_level.txt
